LICENSE.txt
MANIFEST.in
README.rst
VERSION.txt
setup.cfg
setup.py
docs/source/changelog.rst
twapi_connection/__init__.py
twapi_connection/auth.py
twapi_connection/exc.py
twapi_connection/testing.py
twapi_connection.egg-info/PKG-INFO
twapi_connection.egg-info/SOURCES.txt
twapi_connection.egg-info/dependency_links.txt
twapi_connection.egg-info/requires.txt
twapi_connection.egg-info/top_level.txt