Metadata-Version: 1.1
Name: twapi_connection
Version: 2.0a2
Summary: Lightweight abstraction layer for making requests to the 2degrees platform API
Home-page: https://github.com/2degrees/twapi-connection/
Author: 2degrees Limited
Author-email: 2degrees-floss@googlegroups.com
License: BSD (http://dev.2degreesnetwork.com/p/2degrees-license.html)
Keywords: 2degrees
Platform: UNKNOWN
Classifier: Development Status :: 3 - Alpha
Classifier: Intended Audience :: Developers
Classifier: License :: OSI Approved :: BSD License
Classifier: Natural Language :: English
Classifier: Programming Language :: Python :: 3 :: Only
